{
  "db_name": "PostgreSQL",
  "query": "SELECT data, http_mime_type FROM icons WHERE hash = $1",
  "describe": {
    "columns": [
      {
        "ordinal": 0,
        "name": "data",
        "type_info": "Bytea"
      },
      {
        "ordinal": 1,
        "name": "http_mime_type",
        "type_info": "Text"
      }
    ],
    "parameters": {
      "Left": [
        "Bpchar"
      ]
    },
    "nullable": [
      false,
      false
    ]
  },
  "hash": "d8d142f7c2bb25eb449c391e3ca4f791f43d9188cac57b88d7839503a8e7b252"
}
